{
  "build": "v18.06",
  "name": "Search Bar Governed Web Execution Simulation Audit Trail",
  "installed_at": "2026-05-10T03:06:16.830209Z",
  "execution_performed": false,
  "live_web_execution_enabled": false,
  "ai_agent_execution_enabled": false,
  "automatic_updates_enabled": false,
  "runtime_truth_mutation_enabled": false,
  "review_gated": true,
  "confirmation_text_required": true,
  "confirmation_text": "I understand this is an eligibility simulation only",
  "files": [
    "claire\\search_bar\\governed_web_execution_simulation_audit.py",
    "tests\\test_v18_06_governed_web_execution_simulation_audit_trail.py",
    "SEARCH_BAR_GOVERNED_EXECUTION_SIMULATION_AUDIT_REVIEW.bat"
  ]
}
