{
  "run_id": "run-4804b66a8928",
  "status": "insufficient_data",
  "mode": "hybrid",
  "decision_classification": "NO-GO",
  "breakthrough_classification": "LOW",
  "scores": {
    "knowledge_quality_score": 0.6355,
    "source_quality_score": 0.6147,
    "coverage_score": 0.8916,
    "source_count": 3,
    "signal_quality_score": 0.2899,
    "semantic_density_score": 0.546,
    "routing_confidence_score": 0.2913,
    "raw_routing_confidence_score": 0.2913,
    "raw_evidence_signal_score": 0.08,
    "control_signal_score": 0.06,
    "_confidence": 0.2899
  },
  "acquirer_matches": [],
  "domain": "finance",
  "keywords": [
    "discover",
    "emerging",
    "infrastructure",
    "market",
    "opportunities",
    "identify",
    "whether",
    "portfolio",
    "breakthrough",
    "should"
  ],
  "domain_scores": {},
  "knowledge_ingestion": {
    "status": "success",
    "domain": "finance",
    "ingested_at": "2026-05-05T12:49:54.990209+00:00",
    "input_profile": {
      "raw_character_count": 134,
      "normalized_character_count": 134,
      "token_count": 17,
      "unique_token_count": 17,
      "sentence_count": 1,
      "keyword_count": 10,
      "has_substantive_input": true,
      "specificity_score": 0.351,
      "structure_score": 0.1544
    },
    "source_inventory": {
      "available_sources": [
        "market",
        "patent",
        "financial"
      ],
      "empty_sources": [],
      "missing_expected_sources": [],
      "source_count": 3,
      "expected_source_count": 3,
      "source_details": {
        "market": {
          "available": true,
          "field_count": 3,
          "numeric_fields": {
            "growth": 0.07,
            "volatility": 0.16,
            "alignment": 0
          },
          "text_fields": {}
        },
        "patent": {
          "available": true,
          "field_count": 2,
          "numeric_fields": {
            "activity": 0.535,
            "novelty": 0.44
          },
          "text_fields": {}
        },
        "financial": {
          "available": true,
          "field_count": 2,
          "numeric_fields": {
            "health": 0.425,
            "risk": 0.61
          },
          "text_fields": {}
        }
      }
    },
    "source_quality": {
      "level": "usable",
      "score": 0.6147,
      "coverage_quality": 0.96,
      "market_quality": 0.5225,
      "patent_quality": 0.4725,
      "financial_quality": 0.4263,
      "source_count": 3,
      "quality_drivers": [
        "3 connector source(s) available",
        "market growth signal available"
      ]
    },
    "coverage_assessment": {
      "level": "broad",
      "score": 0.8916,
      "domain": "finance",
      "market_present": true,
      "patent_present": true,
      "financial_present": true,
      "keyword_coverage": 10,
      "coverage_gaps": [
        "no major ingestion coverage gap surfaced"
      ]
    },
    "knowledge_quality_score": {
      "level": "usable",
      "score": 0.6355,
      "drivers": [
        "substantive raw input",
        "usable connector source quality",
        "sufficient source/input coverage"
      ]
    },
    "ingestion_contract": {
      "domain": "finance",
      "has_raw_input": true,
      "has_connector_sources": true,
      "source_count": 3,
      "coverage_level": "broad",
      "source_quality_level": "usable",
      "safe_for_downstream_scoring": true,
      "requires_source_enrichment": false
    },
    "lineage": {
      "input_hash": "db9fca2b1347fc54",
      "domain": "finance",
      "keyword_sample": [
        "discover",
        "emerging",
        "infrastructure",
        "market",
        "opportunities",
        "identify",
        "whether",
        "portfolio",
        "breakthrough",
        "should"
      ],
      "source_names": [
        "financial",
        "market",
        "patent"
      ],
      "metadata_keys": [
        "priority",
        "session_id",
        "source",
        "tags",
        "user_id"
      ],
      "lineage_note": "Raw input, extracted keywords, connector-source names, and metadata keys were recorded for deterministic traceability."
    },
    "normalized_input": {
      "text_hash": "db9fca2b1347fc54",
      "preview": "discover emerging ai infrastructure market opportunities and identify whether any portfolio or breakthrough path should be considered.",
      "keyword_count": 10,
      "keywords": [
        "discover",
        "emerging",
        "infrastructure",
        "market",
        "opportunities",
        "identify",
        "whether",
        "portfolio",
        "breakthrough",
        "should"
      ]
    },
    "data_readiness": {
      "state": "usable_for_scoring",
      "source_quality_level": "usable",
      "coverage_level": "broad",
      "minimum_viable_ingestion": true
    },
    "downstream_hints": [
      {
        "area": "connector_sources",
        "hint": "Connector source payloads are available for market, patent, financial, or similar downstream enrichment.",
        "priority": "high"
      },
      {
        "area": "domain",
        "hint": "Use finance as the starting domain context unless signal extraction provides stronger sector routing.",
        "priority": "medium"
      }
    ],
    "recommended_next_actions": [
      {
        "action": "preserve ingestion lineage",
        "purpose": "keep source names, input hash, and metadata traceable through binder/export workflows",
        "priority": "medium"
      }
    ],
    "knowledge_ingestion_thesis": "Knowledge ingestion for finance is usable with score 0.6355. 3 connector source(s) were available and coverage is broad. This input is suitable for downstream deterministic scoring when paired with signal extraction and lifecycle traceability.",
    "confidence": 0.5834
  },
  "signal_extraction": {
    "status": "success",
    "domain": "finance",
    "dominant_sector": "financial_market_intelligence",
    "signal_quality_score": {
      "level": "weak",
      "score": 0.2899,
      "drivers": [
        "basic semantic extraction completed"
      ]
    },
    "semantic_profile": {
      "token_count": 17,
      "unique_token_count": 17,
      "sentence_count": 1,
      "semantic_density_score": 0.546,
      "specificity_score": 0.264,
      "structure_score": 0.1444
    },
    "extracted_keywords": [
      "discover",
      "emerging",
      "infrastructure",
      "market",
      "opportunities",
      "identify",
      "whether",
      "portfolio",
      "breakthrough",
      "should",
      "considered",
      "path"
    ],
    "entities": [
      "Discover"
    ],
    "sector_signals": {
      "climate_insurance": {
        "score": 0.05,
        "matched_terms": [],
        "term_count": 0
      },
      "defense_autonomy": {
        "score": 0.05,
        "matched_terms": [],
        "term_count": 0
      },
      "healthcare_operations": {
        "score": 0.05,
        "matched_terms": [],
        "term_count": 0
      },
      "industrial_supply_chain": {
        "score": 0.05,
        "matched_terms": [],
        "term_count": 0
      },
      "energy_infrastructure": {
        "score": 0.105,
        "matched_terms": [
          "infrastructure"
        ],
        "term_count": 1
      },
      "financial_market_intelligence": {
        "score": 0.16,
        "matched_terms": [
          "market",
          "portfolio"
        ],
        "term_count": 2
      }
    },
    "buyer_signals": {
      "score": 0.1,
      "matched_terms": [],
      "buyer_present": false
    },
    "product_signals": {
      "score": 0.08,
      "matched_terms": [],
      "productizable": false
    },
    "control_signals": {
      "score": 0.06,
      "matched_terms": [],
      "control_gated": false,
      "governance_present": false
    },
    "evidence_signals": {
      "score": 0.08,
      "matched_terms": [],
      "validation_ready": false
    },
    "technical_signals": {
      "score": 0.08,
      "matched_terms": [],
      "implementation_relevant": false
    },
    "routing_evidence": {
      "dominant_sector": "financial_market_intelligence",
      "ranked_sectors": [
        {
          "sector": "financial_market_intelligence",
          "score": 0.16,
          "matched_terms": [
            "market",
            "portfolio"
          ]
        },
        {
          "sector": "energy_infrastructure",
          "score": 0.105,
          "matched_terms": [
            "infrastructure"
          ]
        },
        {
          "sector": "climate_insurance",
          "score": 0.05,
          "matched_terms": []
        },
        {
          "sector": "defense_autonomy",
          "score": 0.05,
          "matched_terms": []
        },
        {
          "sector": "healthcare_operations",
          "score": 0.05,
          "matched_terms": []
        },
        {
          "sector": "industrial_supply_chain",
          "score": 0.05,
          "matched_terms": []
        }
      ],
      "routing_confidence_score": 0.2913,
      "cross_sector_ambiguity": true,
      "routing_note": "financial_market_intelligence leads, but cross-sector ambiguity should be monitored."
    },
    "signal_contract": {
      "dominant_sector": "financial_market_intelligence",
      "has_buyer_signal": false,
      "has_product_signal": false,
      "has_control_signal": false,
      "has_evidence_signal": false,
      "has_technical_signal": false,
      "semantic_density_score": 0.546,
      "specificity_score": 0.264
    },
    "recommended_downstream_attention": [
      {
        "area": "input quality",
        "reason": "input has limited specificity or sparse semantic signals",
        "downstream_use": "treat discovery and breakthrough conclusions as early until richer evidence is provided",
        "priority": "medium"
      },
      {
        "area": "routing",
        "reason": "dominant sector appears to be financial_market_intelligence",
        "downstream_use": "sector-specific engines should preserve this routing unless later evidence strongly overrides it",
        "priority": "high"
      }
    ],
    "signal_extraction_thesis": "Signal extraction identifies financial market intelligence as the dominant routing context with weak signal quality and score 0.2899.",
    "confidence": 0.3736
  },
  "market_gap": {},
  "trend_discovery": {},
  "thesis_formation": {},
  "opportunity_discovery": {},
  "breakthrough_synthesis": {},
  "technical_feasibility": {},
  "productization_path": {},
  "trend_trajectory": {},
  "market_formation": {},
  "moat": {},
  "risk_regulation": {},
  "business_model": {},
  "deal_exit_modeling": {},
  "strategic_positioning": {},
  "engine_details": {
    "signals": {
      "knowledge_ingestion": 0.6355,
      "signal_extraction": 0.2899,
      "routing_confidence": 0.2913,
      "evidence_signal": 0.08
    },
    "knowledge_ingestion": {
      "status": "success",
      "domain": "finance",
      "ingested_at": "2026-05-05T12:49:54.990209+00:00",
      "input_profile": {
        "raw_character_count": 134,
        "normalized_character_count": 134,
        "token_count": 17,
        "unique_token_count": 17,
        "sentence_count": 1,
        "keyword_count": 10,
        "has_substantive_input": true,
        "specificity_score": 0.351,
        "structure_score": 0.1544
      },
      "source_inventory": {
        "available_sources": [
          "market",
          "patent",
          "financial"
        ],
        "empty_sources": [],
        "missing_expected_sources": [],
        "source_count": 3,
        "expected_source_count": 3,
        "source_details": {
          "market": {
            "available": true,
            "field_count": 3,
            "numeric_fields": {
              "growth": 0.07,
              "volatility": 0.16,
              "alignment": 0
            },
            "text_fields": {}
          },
          "patent": {
            "available": true,
            "field_count": 2,
            "numeric_fields": {
              "activity": 0.535,
              "novelty": 0.44
            },
            "text_fields": {}
          },
          "financial": {
            "available": true,
            "field_count": 2,
            "numeric_fields": {
              "health": 0.425,
              "risk": 0.61
            },
            "text_fields": {}
          }
        }
      },
      "source_quality": {
        "level": "usable",
        "score": 0.6147,
        "coverage_quality": 0.96,
        "market_quality": 0.5225,
        "patent_quality": 0.4725,
        "financial_quality": 0.4263,
        "source_count": 3,
        "quality_drivers": [
          "3 connector source(s) available",
          "market growth signal available"
        ]
      },
      "coverage_assessment": {
        "level": "broad",
        "score": 0.8916,
        "domain": "finance",
        "market_present": true,
        "patent_present": true,
        "financial_present": true,
        "keyword_coverage": 10,
        "coverage_gaps": [
          "no major ingestion coverage gap surfaced"
        ]
      },
      "knowledge_quality_score": {
        "level": "usable",
        "score": 0.6355,
        "drivers": [
          "substantive raw input",
          "usable connector source quality",
          "sufficient source/input coverage"
        ]
      },
      "ingestion_contract": {
        "domain": "finance",
        "has_raw_input": true,
        "has_connector_sources": true,
        "source_count": 3,
        "coverage_level": "broad",
        "source_quality_level": "usable",
        "safe_for_downstream_scoring": true,
        "requires_source_enrichment": false
      },
      "lineage": {
        "input_hash": "db9fca2b1347fc54",
        "domain": "finance",
        "keyword_sample": [
          "discover",
          "emerging",
          "infrastructure",
          "market",
          "opportunities",
          "identify",
          "whether",
          "portfolio",
          "breakthrough",
          "should"
        ],
        "source_names": [
          "financial",
          "market",
          "patent"
        ],
        "metadata_keys": [
          "priority",
          "session_id",
          "source",
          "tags",
          "user_id"
        ],
        "lineage_note": "Raw input, extracted keywords, connector-source names, and metadata keys were recorded for deterministic traceability."
      },
      "normalized_input": {
        "text_hash": "db9fca2b1347fc54",
        "preview": "discover emerging ai infrastructure market opportunities and identify whether any portfolio or breakthrough path should be considered.",
        "keyword_count": 10,
        "keywords": [
          "discover",
          "emerging",
          "infrastructure",
          "market",
          "opportunities",
          "identify",
          "whether",
          "portfolio",
          "breakthrough",
          "should"
        ]
      },
      "data_readiness": {
        "state": "usable_for_scoring",
        "source_quality_level": "usable",
        "coverage_level": "broad",
        "minimum_viable_ingestion": true
      },
      "downstream_hints": [
        {
          "area": "connector_sources",
          "hint": "Connector source payloads are available for market, patent, financial, or similar downstream enrichment.",
          "priority": "high"
        },
        {
          "area": "domain",
          "hint": "Use finance as the starting domain context unless signal extraction provides stronger sector routing.",
          "priority": "medium"
        }
      ],
      "recommended_next_actions": [
        {
          "action": "preserve ingestion lineage",
          "purpose": "keep source names, input hash, and metadata traceable through binder/export workflows",
          "priority": "medium"
        }
      ],
      "knowledge_ingestion_thesis": "Knowledge ingestion for finance is usable with score 0.6355. 3 connector source(s) were available and coverage is broad. This input is suitable for downstream deterministic scoring when paired with signal extraction and lifecycle traceability.",
      "confidence": 0.5834
    },
    "signal_extraction": {
      "status": "success",
      "domain": "finance",
      "dominant_sector": "financial_market_intelligence",
      "signal_quality_score": {
        "level": "weak",
        "score": 0.2899,
        "drivers": [
          "basic semantic extraction completed"
        ]
      },
      "semantic_profile": {
        "token_count": 17,
        "unique_token_count": 17,
        "sentence_count": 1,
        "semantic_density_score": 0.546,
        "specificity_score": 0.264,
        "structure_score": 0.1444
      },
      "extracted_keywords": [
        "discover",
        "emerging",
        "infrastructure",
        "market",
        "opportunities",
        "identify",
        "whether",
        "portfolio",
        "breakthrough",
        "should",
        "considered",
        "path"
      ],
      "entities": [
        "Discover"
      ],
      "sector_signals": {
        "climate_insurance": {
          "score": 0.05,
          "matched_terms": [],
          "term_count": 0
        },
        "defense_autonomy": {
          "score": 0.05,
          "matched_terms": [],
          "term_count": 0
        },
        "healthcare_operations": {
          "score": 0.05,
          "matched_terms": [],
          "term_count": 0
        },
        "industrial_supply_chain": {
          "score": 0.05,
          "matched_terms": [],
          "term_count": 0
        },
        "energy_infrastructure": {
          "score": 0.105,
          "matched_terms": [
            "infrastructure"
          ],
          "term_count": 1
        },
        "financial_market_intelligence": {
          "score": 0.16,
          "matched_terms": [
            "market",
            "portfolio"
          ],
          "term_count": 2
        }
      },
      "buyer_signals": {
        "score": 0.1,
        "matched_terms": [],
        "buyer_present": false
      },
      "product_signals": {
        "score": 0.08,
        "matched_terms": [],
        "productizable": false
      },
      "control_signals": {
        "score": 0.06,
        "matched_terms": [],
        "control_gated": false,
        "governance_present": false
      },
      "evidence_signals": {
        "score": 0.08,
        "matched_terms": [],
        "validation_ready": false
      },
      "technical_signals": {
        "score": 0.08,
        "matched_terms": [],
        "implementation_relevant": false
      },
      "routing_evidence": {
        "dominant_sector": "financial_market_intelligence",
        "ranked_sectors": [
          {
            "sector": "financial_market_intelligence",
            "score": 0.16,
            "matched_terms": [
              "market",
              "portfolio"
            ]
          },
          {
            "sector": "energy_infrastructure",
            "score": 0.105,
            "matched_terms": [
              "infrastructure"
            ]
          },
          {
            "sector": "climate_insurance",
            "score": 0.05,
            "matched_terms": []
          },
          {
            "sector": "defense_autonomy",
            "score": 0.05,
            "matched_terms": []
          },
          {
            "sector": "healthcare_operations",
            "score": 0.05,
            "matched_terms": []
          },
          {
            "sector": "industrial_supply_chain",
            "score": 0.05,
            "matched_terms": []
          }
        ],
        "routing_confidence_score": 0.2913,
        "cross_sector_ambiguity": true,
        "routing_note": "financial_market_intelligence leads, but cross-sector ambiguity should be monitored."
      },
      "signal_contract": {
        "dominant_sector": "financial_market_intelligence",
        "has_buyer_signal": false,
        "has_product_signal": false,
        "has_control_signal": false,
        "has_evidence_signal": false,
        "has_technical_signal": false,
        "semantic_density_score": 0.546,
        "specificity_score": 0.264
      },
      "recommended_downstream_attention": [
        {
          "area": "input quality",
          "reason": "input has limited specificity or sparse semantic signals",
          "downstream_use": "treat discovery and breakthrough conclusions as early until richer evidence is provided",
          "priority": "medium"
        },
        {
          "area": "routing",
          "reason": "dominant sector appears to be financial_market_intelligence",
          "downstream_use": "sector-specific engines should preserve this routing unless later evidence strongly overrides it",
          "priority": "high"
        }
      ],
      "signal_extraction_thesis": "Signal extraction identifies financial market intelligence as the dominant routing context with weak signal quality and score 0.2899.",
      "confidence": 0.3736
    }
  },
  "connector_sources": {
    "market": {
      "growth": 0.07,
      "volatility": 0.16,
      "alignment": 0
    },
    "patent": {
      "activity": 0.535,
      "novelty": 0.44
    },
    "financial": {
      "health": 0.425,
      "risk": 0.61
    }
  },
  "signal_trace": {},
  "governed_signals": {
    "status": "success",
    "version": "v5.89.7_signal_governance_layer",
    "raw_signal_count": 1,
    "deduped_signal_count": 1,
    "accepted_signal_count": 1,
    "noise_rejected_count": 0,
    "signals": [
      {
        "signal_id": "sig_5e83970040aa",
        "source_type": "user_input",
        "source_weight": 0.72,
        "title": "Discover emerging AI infrastructure market opportunities and identify whether any",
        "summary": "Discover emerging AI infrastructure market opportunities and identify whether any portfolio or breakthrough path should be considered.",
        "raw_input": "Discover emerging AI infrastructure market opportunities and identify whether any portfolio or breakthrough path should be considered.",
        "created_at": "2026-05-05T12:49:54.989207+00:00",
        "metadata": {
          "intent_id": "intent-f40487ce",
          "domain": "finance",
          "keywords": [
            "discover",
            "emerging",
            "infrastructure",
            "market",
            "opportunities",
            "identify",
            "whether",
            "portfolio",
            "breakthrough",
            "should"
          ]
        },
        "scores": {
          "freshness_score": 1,
          "relevance_score": 1,
          "weak_signal_score": 0.32,
          "momentum_score": 0.18,
          "agreement_score": 0.5,
          "noise_score": 0,
          "quality_score": 0.68,
          "quality_label": "usable",
          "noise_rejection": true,
          "hits": {
            "weak_signal_terms": 1,
            "momentum_terms": 0,
            "relevance_terms": 10,
            "noise_terms": 0
          }
        },
        "governance_status": "accepted",
        "safe_for_lifecycle": true
      }
    ],
    "summary": {
      "signal_count": 1,
      "accepted_signal_count": 1,
      "average_quality_score": 0.68,
      "average_relevance_score": 1,
      "average_momentum_score": 0.18,
      "noise_rejected_count": 0
    }
  },
  "system_design": {},
  "design_portal": {},
  "design_output": {},
  "technology_intelligence": {},
  "portfolio_binder": {},
  "portfolio_optimization": {},
  "export_package": {},
  "export_writer": {},
  "lifecycle": {},
  "lifecycle_stages": [],
  "lifecycle_summary": {},
  "core_lifecycle": {},
  "core_lifecycle_stages": [],
  "core_lifecycle_summary": {},
  "core_completion_gate": {},
  "core_output": {},
  "phase_log": [
    {
      "phase": "signal_extraction",
      "score": 0.29,
      "decision": "TERMINATED",
      "reason": "weak_or_nonexistent_input"
    }
  ],
  "syntalion_ready": false,
  "confidence": 0.2899,
  "intent_id": "intent-f40487ce",
  "executed_at": "2026-05-05T12:49:54.990209+00:00",
  "runtime_trace": {
    "run_id_source": "api_route",
    "intent_id": "intent-f40487ce",
    "orchestrator_file": "C:\\Users\\craig\\OneDrive\\Desktop\\Claire\\src\\claire\\orchestrator\\pipeline_v4.py"
  },
  "validation": {
    "status": "completed",
    "confidence": 0.6999,
    "evidence_count": 13,
    "evidence_strength": 0.6999,
    "validation_ready": true,
    "audit_ready": false,
    "missing_sections": [],
    "timestamp": "2026-05-05T12:49:54.990209+00:00"
  },
  "evidence_chain": [
    {
      "section": "knowledge_ingestion",
      "present": true,
      "evidence_type": "confidence_bearing_section",
      "summary": {
        "status": "success",
        "domain": "finance",
        "sector": null,
        "confidence": 0.5834,
        "has_evidence_signals": false,
        "top_level_keys": [
          "status",
          "domain",
          "ingested_at",
          "input_profile",
          "source_inventory",
          "source_quality",
          "coverage_assessment",
          "knowledge_quality_score",
          "ingestion_contract",
          "lineage",
          "normalized_input",
          "data_readiness"
        ]
      },
      "confidence": 0.5834
    },
    {
      "section": "signal_extraction",
      "present": true,
      "evidence_type": "structured_evidence_signals",
      "summary": {
        "status": "success",
        "domain": "finance",
        "sector": "financial_market_intelligence",
        "confidence": 0.3736,
        "has_evidence_signals": true,
        "top_level_keys": [
          "status",
          "domain",
          "dominant_sector",
          "signal_quality_score",
          "semantic_profile",
          "extracted_keywords",
          "entities",
          "sector_signals",
          "buyer_signals",
          "product_signals",
          "control_signals",
          "evidence_signals"
        ]
      },
      "confidence": 0.3736
    },
    {
      "section": "market_gap",
      "present": true,
      "evidence_type": "structured_section",
      "summary": {
        "status": null,
        "domain": null,
        "sector": null,
        "confidence": null,
        "has_evidence_signals": false,
        "top_level_keys": []
      },
      "confidence": null
    },
    {
      "section": "trend_discovery",
      "present": true,
      "evidence_type": "structured_section",
      "summary": {
        "status": null,
        "domain": null,
        "sector": null,
        "confidence": null,
        "has_evidence_signals": false,
        "top_level_keys": []
      },
      "confidence": null
    },
    {
      "section": "thesis_formation",
      "present": true,
      "evidence_type": "structured_section",
      "summary": {
        "status": null,
        "domain": null,
        "sector": null,
        "confidence": null,
        "has_evidence_signals": false,
        "top_level_keys": []
      },
      "confidence": null
    },
    {
      "section": "opportunity_discovery",
      "present": true,
      "evidence_type": "structured_section",
      "summary": {
        "status": null,
        "domain": null,
        "sector": null,
        "confidence": null,
        "has_evidence_signals": false,
        "top_level_keys": []
      },
      "confidence": null
    },
    {
      "section": "breakthrough_synthesis",
      "present": true,
      "evidence_type": "structured_section",
      "summary": {
        "status": null,
        "domain": null,
        "sector": null,
        "confidence": null,
        "has_evidence_signals": false,
        "top_level_keys": []
      },
      "confidence": null
    },
    {
      "section": "technical_feasibility",
      "present": true,
      "evidence_type": "structured_section",
      "summary": {
        "status": null,
        "domain": null,
        "sector": null,
        "confidence": null,
        "has_evidence_signals": false,
        "top_level_keys": []
      },
      "confidence": null
    },
    {
      "section": "productization_path",
      "present": true,
      "evidence_type": "structured_section",
      "summary": {
        "status": null,
        "domain": null,
        "sector": null,
        "confidence": null,
        "has_evidence_signals": false,
        "top_level_keys": []
      },
      "confidence": null
    },
    {
      "section": "trend_trajectory",
      "present": true,
      "evidence_type": "structured_section",
      "summary": {
        "status": null,
        "domain": null,
        "sector": null,
        "confidence": null,
        "has_evidence_signals": false,
        "top_level_keys": []
      },
      "confidence": null
    },
    {
      "section": "market_formation",
      "present": true,
      "evidence_type": "structured_section",
      "summary": {
        "status": null,
        "domain": null,
        "sector": null,
        "confidence": null,
        "has_evidence_signals": false,
        "top_level_keys": []
      },
      "confidence": null
    },
    {
      "section": "acquirer_matches",
      "present": true,
      "evidence_type": "strategic_matching",
      "summary": {
        "item_count": 0,
        "sample_type": null
      },
      "confidence": null
    },
    {
      "section": "scores",
      "present": true,
      "evidence_type": "quantitative_scores",
      "summary": {
        "status": null,
        "domain": null,
        "sector": null,
        "confidence": null,
        "has_evidence_signals": false,
        "top_level_keys": [
          "knowledge_quality_score",
          "source_quality_score",
          "coverage_score",
          "source_count",
          "signal_quality_score",
          "semantic_density_score",
          "routing_confidence_score",
          "raw_routing_confidence_score",
          "raw_evidence_signal_score",
          "control_signal_score",
          "_confidence"
        ]
      },
      "confidence": null
    }
  ],
  "proof": {
    "status": "completed",
    "confidence": 0.7473,
    "audit_ready": false,
    "validation_ready": true,
    "proof_confidence": 0.7473,
    "summary": {
      "plain_english": "Run run-4804b66a8928 produced a NO-GO decision with LOW breakthrough classification. Proof confidence is 0.7473.",
      "validation_status": "completed",
      "validation_ready": true,
      "audit_ready": false,
      "evidence_sections": 13
    }
  },
  "proof_package": {
    "run_id": "run-4804b66a8928",
    "domain": "finance",
    "decision_classification": "NO-GO",
    "breakthrough_classification": "LOW",
    "proof_confidence": 0.7473,
    "proof_status": "completed",
    "audit_ready": false,
    "validation_ready": true,
    "evidence_count": 13,
    "memory_path": null,
    "summary": {
      "plain_english": "Run run-4804b66a8928 produced a NO-GO decision with LOW breakthrough classification. Proof confidence is 0.7473.",
      "validation_status": "completed",
      "validation_ready": true,
      "audit_ready": false,
      "evidence_sections": 13
    },
    "decision_support": {
      "decision": "NO-GO",
      "breakthrough": "LOW",
      "domain": "finance",
      "primary_scores": {
        "confidence": 0.2899,
        "portfolio_score": null,
        "breakthrough_score": null,
        "opportunity_score": null,
        "acquisition_score": null,
        "knowledge_quality_score": 0.6355,
        "routing_confidence_score": 0.2913,
        "evidence_signal_score": null
      },
      "acquirer_count": 0
    },
    "risk_register": [],
    "evidence_gaps": [],
    "audit_trail": {
      "run_id": "run-4804b66a8928",
      "intent_id": "intent-f40487ce",
      "executed_at": "2026-05-05T12:49:54.990209+00:00",
      "runtime_trace": {
        "run_id_source": "api_route",
        "intent_id": "intent-f40487ce",
        "orchestrator_file": "C:\\Users\\craig\\OneDrive\\Desktop\\Claire\\src\\claire\\orchestrator\\pipeline_v4.py"
      },
      "validation_timestamp": "2026-05-05T12:49:54.990209+00:00",
      "evidence_chain_count": 13,
      "memory_status": null,
      "memory_path": null
    },
    "recommended_binder_artifacts": [
      "full_run_output_json",
      "evidence_chain_json",
      "proof_binder_summary",
      "risk_register",
      "validation_gap_report"
    ]
  },
  "memory": {
    "status": "stored",
    "memory_path": "data\\memory\\runs\\run-4804b66a8928.json",
    "stored_at": "2026-05-05T12:49:54.990209+00:00"
  }
}