{
  "created_at": "2026-05-11T09:42:37.758353Z",
  "launcher_rewired": false,
  "legacy_dashboard_rule": "Existing dashboard is frozen as legacy/reference until parity is proven.",
  "root": "frontend/cockpit/",
  "routes_modified": false,
  "runtime_behavior_changed": false,
  "search_rule": "Search is permanent Claire Command Surface.",
  "source_of_truth_rule": "Backend runtime APIs and canonical payload contracts own truth.",
  "status": "created_as_permanent_cockpit_root",
  "version": "v19.66"
}
